{
    "images": [
        {
            "startdate": "20210219",
            "fullstartdate": "202102191600",
            "enddate": "20210220",
            "url": "/th?id=OHR.AABday_ZH-CN8551609592_1920x1080.jpg&rf=LaDigue_1920x1080.jpg&pid=hp",
            "urlbase": "/th?id=OHR.AABday_ZH-CN8551609592",
            "copyright": "暴风雪散去，加利福尼亚优胜美地国家公园 (© Jeff Lewis/Tandem Stills + Motion)",
            "copyrightlink": "https://www.bing.com/search?q=%E4%BC%98%E8%83%9C%E7%BE%8E%E5%9C%B0%E5%9B%BD%E5%AE%B6%E5%85%AC%E5%9B%AD&form=hpcapt&mkt=zh-cn",
            "title": "",
            "quiz": "/search?q=Bing+homepage+quiz&filters=WQOskey:%22HPQuiz_20210219_AABday%22&FORM=HPQUIZ",
            "wp": true,
            "hsh": "d6edfb97190f49d853e4eb6c924ac06f",
            "drk": 1,
            "top": 1,
            "bot": 1,
            "hs": []
        },
        {
            "startdate": "20210218",
            "fullstartdate": "202102181600",
            "enddate": "20210219",
            "url": "/th?id=OHR.Parrotfish_ZH-CN8442237302_1920x1080.jpg&rf=LaDigue_1920x1080.jpg&pid=hp",
            "urlbase": "/th?id=OHR.Parrotfish_ZH-CN8442237302",
            "copyright": "东内格罗斯省沿海的鹦嘴鱼，菲律宾 (© Tim Fitzharris/Minden Pictures)",
            "copyrightlink": "https://www.bing.com/search?q=%E9%B9%A6%E5%98%B4%E9%B1%BC&form=hpcapt&mkt=zh-cn",
            "title": "",
            "quiz": "/search?q=Bing+homepage+quiz&filters=WQOskey:%22HPQuiz_20210218_Parrotfish%22&FORM=HPQUIZ",
            "wp": true,
            "hsh": "e833016d91e18425061f96a6c190f98e",
            "drk": 1,
            "top": 1,
            "bot": 1,
            "hs": []
        },
        {
            "startdate": "20210217",
            "fullstartdate": "202102171600",
            "enddate": "20210218",
            "url": "/th?id=OHR.VerzascaValley_ZH-CN8308636990_1920x1080.jpg&rf=LaDigue_1920x1080.jpg&pid=hp",
            "urlbase": "/th?id=OHR.VerzascaValley_ZH-CN8308636990",
            "copyright": "拉韦尔泰佐附近一条河里的石头，瑞士塞斯卡山谷 (© Robert Seitz/Offset by Shutterstock)",
            "copyrightlink": "https://www.bing.com/search?q=%E6%8B%89%E9%9F%A6%E5%B0%94%E6%B3%B0%E4%BD%90&form=hpcapt&mkt=zh-cn",
            "title": "",
            "quiz": "/search?q=Bing+homepage+quiz&filters=WQOskey:%22HPQuiz_20210217_VerzascaValley%22&FORM=HPQUIZ",
            "wp": true,
            "hsh": "0da5abeb96aee2b99f701c4554261bc8",
            "drk": 1,
            "top": 1,
            "bot": 1,
            "hs": []
        },
        {
            "startdate": "20210216",
            "fullstartdate": "202102161600",
            "enddate": "20210217",
            "url": "/th?id=OHR.PeritoMorenoArgentina_ZH-CN8205335022_1920x1080.jpg&rf=LaDigue_1920x1080.jpg&pid=hp",
            "urlbase": "/th?id=OHR.PeritoMorenoArgentina_ZH-CN8205335022",
            "copyright": "冰川国家公园中的佩里托莫雷诺冰川，阿根廷 (© Juergen Schonnop/Getty Images)",
            "copyrightlink": "https://www.bing.com/search?q=%E4%BD%A9%E9%87%8C%E6%89%98%E8%8E%AB%E9%9B%B7%E8%AF%BA%E5%86%B0%E5%B7%9D&form=hpcapt&mkt=zh-cn",
            "title": "",
            "quiz": "/search?q=Bing+homepage+quiz&filters=WQOskey:%22HPQuiz_20210216_PeritoMorenoArgentina%22&FORM=HPQUIZ",
            "wp": true,
            "hsh": "c7c260ee411338e7c69453e18947a7d0",
            "drk": 1,
            "top": 1,
            "bot": 1,
            "hs": []
        },
        {
            "startdate": "20210215",
            "fullstartdate": "202102151600",
            "enddate": "20210216",
            "url": "/th?id=OHR.PurpleFlowers_ZH-CN7975901617_1920x1080.jpg&rf=LaDigue_1920x1080.jpg&pid=hp",
            "urlbase": "/th?id=OHR.PurpleFlowers_ZH-CN7975901617",
            "copyright": "屋前的鲜花和铁艺围栏，路易斯安那州新奥尔良 (© Lauren Mitchell/Offset by Shutterstock)",
            "copyrightlink": "https://www.bing.com/search?q=%E9%93%81%E8%89%BA%E5%9B%B4%E6%A0%8F&form=hpcapt&mkt=zh-cn",
            "title": "",
            "quiz": "/search?q=Bing+homepage+quiz&filters=WQOskey:%22HPQuiz_20210215_PurpleFlowers%22&FORM=HPQUIZ",
            "wp": true,
            "hsh": "a77d468cd42ac3e5ec9f03ffc202e9b4",
            "drk": 1,
            "top": 1,
            "bot": 1,
            "hs": []
        },
        {
            "startdate": "20210214",
            "fullstartdate": "202102141600",
            "enddate": "20210215",
            "url": "/th?id=OHR.OnkaparingaRiver_ZH-CN7750372049_1920x1080.jpg&rf=LaDigue_1920x1080.jpg&pid=hp",
            "urlbase": "/th?id=OHR.OnkaparingaRiver_ZH-CN7750372049",
            "copyright": "安加白令嘉河与诺朗加港，南澳大利亚州 (© plainpicture/AWL/Marco Bottigelli)",
            "copyrightlink": "https://www.bing.com/search?q=%E8%AF%BA%E6%9C%97%E5%8A%A0%E6%B8%AF&form=hpcapt&mkt=zh-cn",
            "title": "",
            "quiz": "/search?q=Bing+homepage+quiz&filters=WQOskey:%22HPQuiz_20210214_OnkaparingaRiver%22&FORM=HPQUIZ",
            "wp": true,
            "hsh": "f4ff38faefa82d5e0cc6e4308941cb51",
            "drk": 1,
            "top": 1,
            "bot": 1,
            "hs": []
        },
        {
            "startdate": "20210213",
            "fullstartdate": "202102131600",
            "enddate": "20210214",
            "url": "/th?id=OHR.OceanHeart_ZH-CN2697021215_1920x1080.jpg&rf=LaDigue_1920x1080.jpg&pid=hp",
            "urlbase": "/th?id=OHR.OceanHeart_ZH-CN2697021215",
            "copyright": "海浪冲击着悉尼海岸的一个心形岩石岛，澳大利亚 (© Kristian Bell/Getty Images)",
            "copyrightlink": "https://www.bing.com/search?q=%E5%BF%83%E5%BD%A2%E5%B2%A9%E7%9F%B3%E5%B2%9B&form=hpcapt&mkt=zh-cn",
            "title": "",
            "quiz": "/search?q=Bing+homepage+quiz&filters=WQOskey:%22HPQuiz_20210213_OceanHeart%22&FORM=HPQUIZ",
            "wp": true,
            "hsh": "0c62ab4ca65f2e32bca2035f687a8570",
            "drk": 1,
            "top": 1,
            "bot": 1,
            "hs": []
        },
        {
            "startdate": "20210212",
            "fullstartdate": "202102121600",
            "enddate": "20210213",
            "url": "/th?id=OHR.BluebirdsEastern_ZH-CN2598458880_1920x1080.jpg&rf=LaDigue_1920x1080.jpg&pid=hp",
            "urlbase": "/th?id=OHR.BluebirdsEastern_ZH-CN2598458880",
            "copyright": "四只东蓝鸲，北卡罗莱纳州夏洛特 (© Elizabeth W. Kearley/Getty Images)",
            "copyrightlink": "https://www.bing.com/search?q=%E4%B8%9C%E8%93%9D%E9%B8%B2&form=hpcapt&mkt=zh-cn",
            "title": "",
            "quiz": "/search?q=Bing+homepage+quiz&filters=WQOskey:%22HPQuiz_20210212_BluebirdsEastern%22&FORM=HPQUIZ",
            "wp": true,
            "hsh": "375fc4d50dba8cc12f59c06a52694a72",
            "drk": 1,
            "top": 1,
            "bot": 1,
            "hs": []
        }
    ]
}